{"cameraMode":{"drawMode":0,"name":"Shaded","section":"Shading Mode"},"sceneLighting":true,"audioPlay":false,"sceneViewState":{"m_AlwaysRefresh":false,"showFog":true,"showSkybox":true,"showFlares":true,"showImageEffects":true,"showParticleSystems":true,"showVisualEffectGraphs":true,"m_FxEnabled":true},"in2DMode":false,"pivot":{"x":-1.6284563541412354,"y":-293.1521911621094,"z":6.492212295532227},"rotation":{"x":-0.6773473024368286,"y":-0.013902736827731133,"z":0.012805311009287835,"w":-0.7354297637939453},"size":155.3735809326172,"orthographic":false}